poplar/__init__.py
poplar/distributions.py
poplar/likelihood.py
poplar/selection.py
poplar/utilities.py
poplar/nn/__init__.py
poplar/nn/networks.py
poplar/nn/plot.py
poplar/nn/rescaling.py
poplar/nn/training.py
poplar-0.2.dist-info/LICENSE
poplar-0.2.dist-info/METADATA
poplar-0.2.dist-info/WHEEL
poplar-0.2.dist-info/top_level.txt
poplar-0.2.dist-info/RECORD
