Metadata-Version: 2.1
Name: poplar
Version: 0.2
Summary: A python package for modelling selection effects with machine learning
Author-email: Christian Chapman-Bird <c.chapman-bird.1@research.gla.ac.uk>
License: GPL-3.0-or-later
Project-URL: Bug Tracker, https://github.com/CChapmanbird/poplar/issues
Project-URL: Source Code, https://github.com/CChapmanbird/poplar
Classifier: Development Status :: 5 - Production/Stable
Classifier: Intended Audience :: Science/Research
Classifier: License :: OSI Approved :: GNU General Public License v3 or later (GPLv3+)
Classifier: Natural Language :: English
Classifier: Operating System :: OS Independent
Classifier: Programming Language :: Python
Classifier: Programming Language :: Python :: 3
Classifier: Programming Language :: Python :: 3.7
Classifier: Programming Language :: Python :: 3.8
Classifier: Programming Language :: Python :: 3.9
Classifier: Programming Language :: Python :: 3.10
Classifier: Programming Language :: Python :: 3.11
Classifier: Topic :: Scientific/Engineering :: Astronomy
Classifier: Topic :: Scientific/Engineering :: Physics
Requires-Python: >=3.8
License-File: LICENSE
Requires-Dist: matplotlib (>=3.3.0)
Requires-Dist: seaborn
Requires-Dist: numpy (>=1.17)
Requires-Dist: scipy (>=1.2.0)
Requires-Dist: tqdm
Requires-Dist: dill
Requires-Dist: pathlib
Requires-Dist: torch (>=1.7.0)
